pre_commit_copyright/__init__.py
pre_commit_copyright-0.1.4.dist-info/entry_points.txt
pre_commit_copyright-0.1.4.dist-info/METADATA
pre_commit_copyright-0.1.4.dist-info/WHEEL
pre_commit_copyright-0.1.4.dist-info/RECORD
